{
  "enabled": true,
  "neededInstalledMods": [],
  "neededUninstalledMods": [],
  "spawns": [
    {
      "id": "darkrai",
      "pokemon": "darkrai",
      "presets": ["natural", "wild"],
      "type": "pokemon",
      "context": "grounded",
      "bucket": "ultra-rare",
      "level": "50-70",
      "weight": 1.0,
      "condition": {
        "biomes": ["#cobblemon:is_magical"],
        "moonPhase": 5
      }
    },
    {
      "id": "darkrai-1",
      "pokemon": "darkrai",
      "presets": ["natural", "wild"],
      "type": "pokemon",
      "context": "grounded",
      "bucket": "ultra-rare",
      "level": "50-70",
      "weight": 1.0,
      "condition": {
        "biomes": ["#cobblemon:is_deep_dark"]
      }
    }
  ]
}
